fabricauthenticator/__init__.py
fabricauthenticator/fabricauthenticator.py
fabricauthenticator-1.3.4.dist-info/LICENSE
fabricauthenticator-1.3.4.dist-info/WHEEL
fabricauthenticator-1.3.4.dist-info/METADATA
fabricauthenticator-1.3.4.dist-info/RECORD
