Metadata-Version: 2.1
Name: fabricauthenticator
Version: 1.3.4
Summary: Fabric OAuth Authenticator
Keywords: Swagger,Fabric OAuth Authenticator
Author-email: Komal Thareja <kthare10@renci.org>
Requires-Python: >=3.7
Classifier: Programming Language :: Python :: 3
Classifier: License :: OSI Approved :: MIT License
Classifier: Operating System :: OS Independent
Requires-Dist: jupyterhub>=1.0
Requires-Dist: oauthenticator==15.1.0
Requires-Dist: requests
Requires-Dist: ldap3
Project-URL: Home, https://fabric-testbed.net/
Project-URL: Sources, https://github.com/fabric-testbed/fabricauthenticator
